[{"bucket": -0.5, "id": "-0.5", "height": 8}, {"bucket": 1.0, "id": "1.0", "height": 12}, {"bucket": -2.7, "id": "-2.7", "height": 1}, {"bucket": 0.6, "id": "0.6", "height": 12}, {"bucket": 0.0, "id": "0.0", "height": 15}, {"bucket": -2.4, "id": "-2.4", "height": 1}, {"bucket": 1.1, "id": "1.1", "height": 1}, {"bucket": 2.0, "id": "2.0", "height": 3}, {"bucket": -2.2, "id": "-2.2", "height": 2}, {"bucket": -1.3, "id": "-1.3", "height": 7}, {"bucket": 0.7, "id": "0.7", "height": 5}, {"bucket": -0.2, "id": "-0.2", "height": 12}, {"bucket": -0.1, "id": "-0.1", "height": 11}, {"bucket": -1.4, "id": "-1.4", "height": 5}, {"bucket": 0.5, "id": "0.5", "height": 12}, {"bucket": 1.9, "id": "1.9", "height": 1}, {"bucket": 2.1, "id": "2.1", "height": 2}, {"bucket": -0.9, "id": "-0.9", "height": 6}, {"bucket": 1.3, "id": "1.3", "height": 5}, {"bucket": -0.3, "id": "-0.3", "height": 7}, {"bucket": -2.1, "id": "-2.1", "height": 1}, {"bucket": -0.6, "id": "-0.6", "height": 8}, {"bucket": -1.5, "id": "-1.5", "height": 4}, {"bucket": -0.4, "id": "-0.4", "height": 15}, {"bucket": 1.5, "id": "1.5", "height": 2}, {"bucket": 0.4, "id": "0.4", "height": 12}, {"bucket": 0.3, "id": "0.3", "height": 11}, {"bucket": 1.7, "id": "1.7", "height": 2}, {"bucket": 0.8, "id": "0.8", "height": 10}, {"bucket": -1.8, "id": "-1.8", "height": 4}, {"bucket": -0.8, "id": "-0.8", "height": 11}, {"bucket": 1.4, "id": "1.4", "height": 4}, {"bucket": -1.1, "id": "-1.1", "height": 6}, {"bucket": 2.5, "id": "2.5", "height": 1}, {"bucket": 1.8, "id": "1.8", "height": 3}, {"bucket": 1.6, "id": "1.6", "height": 2}, {"bucket": 0.1, "id": "0.1", "height": 10}, {"bucket": 0.2, "id": "0.2", "height": 14}, {"bucket": -0.7, "id": "-0.7", "height": 11}, {"bucket": 0.9, "id": "0.9", "height": 6}, {"bucket": -1.9, "id": "-1.9", "height": 3}, {"bucket": -2.3, "id": "-2.3", "height": 2}, {"bucket": 1.2, "id": "1.2", "height": 5}, {"bucket": -1.7, "id": "-1.7", "height": 3}, {"bucket": -1.6, "id": "-1.6", "height": 7}, {"bucket": -2.0, "id": "-2.0", "height": 1}, {"bucket": -1.2, "id": "-1.2", "height": 5}, {"bucket": -1.0, "id": "-1.0", "height": 9}]